not_covered_lines/__init__.py
not_covered_lines/not_covered_lines.py
not_covered_lines-0.0.2.dist-info/LICENSE
not_covered_lines-0.0.2.dist-info/METADATA
not_covered_lines-0.0.2.dist-info/WHEEL
not_covered_lines-0.0.2.dist-info/top_level.txt
not_covered_lines-0.0.2.dist-info/RECORD
