Metadata-Version: 2.1
Name: not-covered-lines
Version: 0.0.2
Summary: Finds a python-thing, like a class, a function or a variable by string and loads it
Home-page: https://github.com/tom-010/not_covered_lines
Author: Thomas Deniffel
Author-email: tdeniffel@gmail.com
License: Apache2
Platform: UNKNOWN
Classifier: Development Status :: 4 - Beta
Classifier: Intended Audience :: Developers
Classifier: Programming Language :: Python
Classifier: Programming Language :: Python :: 3 :: Only
Classifier: Programming Language :: Python :: 3.6
Classifier: Programming Language :: Python :: 3.7
Requires-Python: >=3
Requires-Dist: coverage
